{"metadata":{"usedHelpers":[],"marked":[],"modules":{"imports":[],"exports":{"exported":[],"specifiers":[]}}},"options":{"filename":"/client/recipes/Recipes.js","filenameRelative":"/client/recipes/Recipes.js","env":{},"retainLines":false,"highlightCode":true,"suppressDeprecationMessages":false,"presets":[],"plugins":[[[],{"polyfill":false}],[[],null],[[],null],[[],null],[[],null],[[],null],[[],null],[[],null],[[],null],[[],null],[[],null],[[],null],[[],null],[[],null],[[],null],[[],null],[[],{"loose":true}],[[],{"loose":true}],[[],null],[[],{"loose":true}],[[],null],[[],null],[[],null],[[],null],[[],null],[[],null],[[],null],[[],{"loose":true}],[[],null],[[],null],[[],null],[[],null],[[],null],[[],null],[[],null],[[],null]],"ignore":[],"code":true,"metadata":true,"ast":false,"comments":true,"compact":false,"minified":false,"sourceMap":true,"sourceMaps":true,"sourceMapTarget":"/client/recipes/Recipes.js.map","sourceFileName":"/client/recipes/Recipes.js","babelrc":false,"sourceType":"module","moduleIds":false,"passPerPreset":false,"basename":"Recipes"},"ignored":false,"code":"Meteor.subscribe('recipes');\n\nconsole.log(Meteor.settings['public'].ga.account);","ast":null,"map":{"version":3,"sources":["/client/recipes/Recipes.js"],"names":[],"mappings":"AAAA,OAAO,SAAP,CAAiB,SAAjB;;AAEA,QAAQ,GAAR,CAAY,OAAO,QAAP,WAAuB,EAAvB,CAA0B,OAAtC","file":"/client/recipes/Recipes.js.map","sourcesContent":["Meteor.subscribe('recipes');\n\nconsole.log(Meteor.settings.public.ga.account)\n"]},"hash":"15d02204981cf075a6afe004723d771ef6835229"}
